
  { "stem" : "dethron",
    "instances" : 
    [ 
      { "docId" : "InchbaldVol4Rem1KingLear1808",
        "docUri" : "InchbaldVol4Rem1KingLear1808.html",
        "score" : 1,
        "contexts" : 
        [ 
          { "form" : "dethrone",
            "weight" : "1",
            "pos" : 209,
            "context" : "...and proceeding to the metropolis, in order to <mark>dethrone<\/mark> him, he called, as the historian relates,...",
            "fid" : "para18" } ] },
      
      { "docId" : "InchbaldVol2Rem4KingHenryV1808",
        "docUri" : "InchbaldVol2Rem4KingHenryV1808.html",
        "score" : 1,
        "contexts" : 
        [ 
          { "form" : "dethroned",
            "weight" : "1",
            "pos" : 428,
            "context" : "...left no more than one child, who was <mark>dethroned<\/mark> and murdered.11 ",
            "fid" : "para24" } ] } ] }