
  { "stem" : "fed",
    "instances" : 
    [ 
      { "docId" : "TaylorEPoetsRuralCowper1821",
        "docUri" : "TaylorEPoetsRuralCowper1821.html",
        "score" : 1,
        "contexts" : 
        [ 
          { "form" : "fed",
            "weight" : "1",
            "pos" : 355,
            "context" : "...disdain the aliment upon which mind and heart are <mark>fed<\/mark>, and both are in imminent danger of starvation...",
            "fid" : "para14" } ] },
      
      { "docId" : "BarbRichardBritNov1810",
        "docUri" : "BarbRichardBritNov1810.html",
        "score" : 1,
        "contexts" : 
        [ 
          { "form" : "fed",
            "weight" : "1",
            "pos" : 5764,
            "context" : "..., and seeing no equal, he was constantly <mark>fed<\/mark> with adulation [Page xlv]and even his...",
            "fid" : "para67" } ] },
      
      { "docId" : "BarbOriginProgBritNov1810",
        "docUri" : "BarbOriginProgBritNov1810.html",
        "score" : 1,
        "contexts" : 
        [ 
          { "form" : "fed",
            "weight" : "1",
            "pos" : 1525,
            "context" : "...romances, (a course of reading which no doubt <mark>fed<\/mark> and inflamed his fine imagination) has borrowed from...",
            "fid" : "para21" } ] },
      
      { "docId" : "BarbLifeRichardson1804",
        "docUri" : "BarbLifeRichardson1804.html",
        "score" : 1,
        "contexts" : 
        [ 
          { "form" : "fed",
            "weight" : "1",
            "pos" : 12690,
            "context" : "...is said that he was vain; he was <mark>fed<\/mark> with praise, and, with regard to that diet...",
            "fid" : "para145" } ] },
      
      { "docId" : "BaillieIntDis1798",
        "docUri" : "BaillieIntDis1798.html",
        "score" : 1,
        "contexts" : 
        [ 
          { "form" : "fed",
            "weight" : "1",
            "pos" : 1921,
            "context" : "...is very strong; and if we are richly <mark>fed<\/mark> with what we have a good relish for, we...",
            "fid" : "para30" } ] },
      
      { "docId" : "BarbCollins1797",
        "docUri" : "BarbCollins1797.html",
        "score" : 1,
        "contexts" : 
        [ 
          { "form" : "fed",
            "weight" : "1",
            "pos" : 435,
            "context" : "...of ease and leisure; his imagination should be <mark>fed<\/mark> with novelty, and his ear soothed by praise...",
            "fid" : "para15" } ] } ] }