
  { "stem" : "foolish",
    "instances" : 
    [ 
      { "docId" : "LandonBulwer1831",
        "docUri" : "LandonBulwer1831.html",
        "score" : 1,
        "contexts" : 
        [ 
          { "form" : "foolish",
            "weight" : "1",
            "pos" : 2864,
            "context" : "...sneers; the coarse and false statements; the <mark>foolish<\/mark> opinions of a set whose incognito is indeed their...",
            "fid" : "para23" } ] },
      
      { "docId" : "InchbaldVol4Rem2Cymbeline1808",
        "docUri" : "InchbaldVol4Rem2Cymbeline1808.html",
        "score" : 1,
        "contexts" : 
        [ 
          { "form" : "foolish",
            "weight" : "1",
            "pos" : 267,
            "context" : "...the author to make this youthful forester lay his <mark>foolish<\/mark> enemy dead at his feet, and then be...",
            "fid" : "para18" } ] },
      
      { "docId" : "BaillieIntDis1798",
        "docUri" : "BaillieIntDis1798.html",
        "score" : 1,
        "contexts" : 
        [ 
          { "form" : "foolish",
            "weight" : "1",
            "pos" : 1953,
            "context" : "...perceive and be delighted with it, though we are <mark>foolish<\/mark> enough to admire at the same time, all...",
            "fid" : "para30" } ] } ] }