
  { "stem" : "loin",
    "instances" : 
    [ 
      { "docId" : "MoodyRevMalheur1804",
        "docUri" : "MoodyRevMalheur1804.html",
        "score" : 2,
        "contexts" : 
        [ 
          { "form" : "Loin",
            "weight" : "1",
            "pos" : 436,
            "context" : "...du fond des cachots vous babitez les cieux.<mark>Loin<\/mark> donc de l'homme impie, exécrable maxime,Qui...",
            "fid" : "line43" },
          
          { "form" : "loin",
            "weight" : "1",
            "pos" : 712,
            "context" : "...sa fatale guerre,De François égorgés couvroit au <mark>loin<\/mark> la terre,Et le sujet des rois,...",
            "fid" : "line77" } ] } ] }