
  { "stem" : "objection",
    "instances" : 
    [ 
      { "docId" : "TaylorEPoetsRuralCowper1821",
        "docUri" : "TaylorEPoetsRuralCowper1821.html",
        "score" : 1,
        "contexts" : 
        [ 
          { "form" : "objectionable",
            "weight" : "1",
            "pos" : 753,
            "context" : "...and respecting religion ourselves, we cannot see any thing <mark>objectionable<\/mark> in giving her cause all the advantage which good...",
            "fid" : "para16" } ] },
      
      { "docId" : "BarbRichardBritNov1810",
        "docUri" : "BarbRichardBritNov1810.html",
        "score" : 1,
        "contexts" : 
        [ 
          { "form" : "objectionable",
            "weight" : "1",
            "pos" : 3344,
            "context" : "...of by degrees. His Clarissa is far less <mark>objectionable<\/mark> than his Pamela; his Grandison not at all...",
            "fid" : "para40" } ] },
      
      { "docId" : "BarbLifeRichardson1804",
        "docUri" : "BarbLifeRichardson1804.html",
        "score" : 1,
        "contexts" : 
        [ 
          { "form" : "objectionable",
            "weight" : "1",
            "pos" : 7473,
            "context" : "...of by degrees. His Clarissa is far less <mark>objectionable<\/mark> than his Pamela; his Grandison not e 4...",
            "fid" : "para93" } ] },
      
      { "docId" : "MoodyRevSchoFash1801",
        "docUri" : "MoodyRevSchoFash1801.html",
        "score" : 1,
        "contexts" : 
        [ 
          { "form" : "objectionable",
            "weight" : "1",
            "pos" : 123,
            "context" : "...present times may have other fashions of an equally <mark>objectionable<\/mark> nature. In the dedication to Fashion, however...",
            "fid" : "para14" } ] },
      
      { "docId" : "BuskMMmeDudevantNovs1834",
        "docUri" : "BuskMMmeDudevantNovs1834.html",
        "score" : 1,
        "contexts" : 
        [ 
          { "form" : "objectionable",
            "weight" : "1",
            "pos" : 4282,
            "context" : "...Rose et Blanche, in every respect a less <mark>objectionable<\/mark> work, and less inferior to Indiana, but...",
            "fid" : "para148" } ] } ] }