
  { "stem" : "stigmatis",
    "instances" : 
    [ 
      { "docId" : "ShelleyModItRom1838corpus",
        "docUri" : "ShelleyModItRom1838corpus.html",
        "score" : 2,
        "contexts" : 
        [ 
          { "form" : "stigmatised",
            "weight" : "1",
            "pos" : 1288,
            "context" : "...favourite topic with the Italians. Being so often <mark>stigmatised<\/mark> as cowards, they turn with pride to this..." },
          
          { "form" : "stigmatise",
            "weight" : "1",
            "pos" : 8277,
            "context" : "...even to contemporary authors. It was easy to <mark>stigmatise<\/mark> his act as the result of cowardice; and,...",
            "fid" : "21" } ] },
      
      { "docId" : "ShelleyModItRomII1838",
        "docUri" : "ShelleyModItRomII1838.html",
        "score" : 1,
        "contexts" : 
        [ 
          { "form" : "stigmatise",
            "weight" : "1",
            "pos" : 3557,
            "context" : "...even to contemporary authors. It was easy to <mark>stigmatise<\/mark> his act as the result of cowardice; and,...",
            "fid" : "note11" } ] },
      
      { "docId" : "ShelleyModItRomI1838",
        "docUri" : "ShelleyModItRomI1838.html",
        "score" : 1,
        "contexts" : 
        [ 
          { "form" : "stigmatised",
            "weight" : "1",
            "pos" : 1288,
            "context" : "...favourite topic with the Italians. Being so often <mark>stigmatised<\/mark> as cowards, they turn with pride to this...",
            "fid" : "para24" } ] } ] }