
  { "stem" : "suffic",
    "instances" : 
    [ 
      { "docId" : "ShelleyModItRom1838corpus",
        "docUri" : "ShelleyModItRom1838corpus.html",
        "score" : 2,
        "contexts" : 
        [ 
          { "form" : "sufficing",
            "weight" : "1",
            "pos" : 1901,
            "context" : "...secret chamber of his enemy's fortress, for no <mark>sufficing<\/mark> reason, and then, unexpectedly, the most disgusting..." },
          
          { "form" : "suffice",
            "weight" : "1",
            "pos" : 5319,
            "context" : "...Yet so much of life remains to me to <mark>suffice<\/mark> for such acts, that when your grandchildren ask..." } ] },
      
      { "docId" : "ShelleyEngInItaly1826",
        "docUri" : "ShelleyEngInItaly1826.html",
        "score" : 2,
        "contexts" : 
        [ 
          { "form" : "suffice",
            "weight" : "1",
            "pos" : 484,
            "context" : "...who fancy that a little Anglo-French will <mark>suffice<\/mark> to convey intelligence of their wants and wishes to...",
            "fid" : "para15" },
          
          { "form" : "suffices",
            "weight" : "1",
            "pos" : 2090,
            "context" : "...land, and whose share of corn and wine <mark>suffices<\/mark> to maintain that family without extra purchase, considers...",
            "fid" : "para23" } ] },
      
      { "docId" : "BarbFieldingBritNov1810",
        "docUri" : "BarbFieldingBritNov1810.html",
        "score" : 2,
        "contexts" : 
        [ 
          { "form" : "suffice",
            "weight" : "1",
            "pos" : 2149,
            "context" : "...novel would be almost to transcribe the work; <mark>suffice<\/mark> it to mention one or two. ",
            "fid" : "para34" },
          
          { "form" : "sufficed",
            "weight" : "1",
            "pos" : 2801,
            "context" : "...in his own little domain, and their estates <mark>sufficed<\/mark> them to reside among their tenants and dependants in...",
            "fid" : "para39" } ] },
      
      { "docId" : "BuskMMmeDudevantNovs1834",
        "docUri" : "BuskMMmeDudevantNovs1834.html",
        "score" : 2,
        "contexts" : 
        [ 
          { "form" : "sufficed",
            "weight" : "1",
            "pos" : 2871,
            "context" : "...must observe that the high polish of their manners <mark>sufficed<\/mark> to insure general external decorum. And yet,...",
            "fid" : "para113" },
          
          { "form" : "suffice",
            "weight" : "1",
            "pos" : 3637,
            "context" : "...then his own. Of the nocturnal scene that ensues <mark>suffice<\/mark> it to say, that the lover, in...",
            "fid" : "para135" } ] },
      
      { "docId" : "ShelleyModItRomII1838",
        "docUri" : "ShelleyModItRomII1838.html",
        "score" : 1,
        "contexts" : 
        [ 
          { "form" : "suffice",
            "weight" : "1",
            "pos" : 783,
            "context" : "...Yet so much of life remains to me to <mark>suffice<\/mark> for such acts, that when your grandchildren ask...",
            "fid" : "para25" } ] },
      
      { "docId" : "ShelleyRevLovesPoets1829",
        "docUri" : "ShelleyRevLovesPoets1829.html",
        "score" : 1,
        "contexts" : 
        [ 
          { "form" : "suffice",
            "weight" : "1",
            "pos" : 161,
            "context" : "...changes of dress, and gambling. Yet these <mark>suffice<\/mark> not, nor professions, trades, nor ambition,...",
            "fid" : "para15" } ] },
      
      { "docId" : "ShelleyModItRomI1838",
        "docUri" : "ShelleyModItRomI1838.html",
        "score" : 1,
        "contexts" : 
        [ 
          { "form" : "sufficing",
            "weight" : "1",
            "pos" : 1901,
            "context" : "...secret chamber of his enemy's fortress, for no <mark>sufficing<\/mark> reason, and then, unexpectedly, the most disgusting...",
            "fid" : "para28" } ] } ] }