
  { "stem" : "sunshin",
    "instances" : 
    [ 
      { "docId" : "LandonHemans1835",
        "docUri" : "LandonHemans1835.html",
        "score" : 4,
        "contexts" : 
        [ 
          { "form" : "sunshine",
            "weight" : "1",
            "pos" : 345,
            "context" : "...their youth as in a burial urn,Where <mark>sunshine<\/mark> may not find it.7  ",
            "fid" : "line4" },
          
          { "form" : "sunshine",
            "weight" : "1",
            "pos" : 571,
            "context" : "...sad to-morrow.10   The most intense <mark>sunshine<\/mark> casts the deepest shadow. Such mirth does not...",
            "fid" : "para19" },
          
          { "form" : "sunshine",
            "weight" : "1",
            "pos" : 1560,
            "context" : "...caverns of doubt into the free air and blessed <mark>sunshine<\/mark> of conviction and belief.\" I asked her if...",
            "fid" : "para28" },
          
          { "form" : "sunshine",
            "weight" : "1",
            "pos" : 1739,
            "context" : "...the clouds gather more darkly around for the passing <mark>sunshine<\/mark>. The heart sinks back on its solitary desolation...",
            "fid" : "para29" } ] },
      
      { "docId" : "LandonCritChateaubriand1836",
        "docUri" : "LandonCritChateaubriand1836.html",
        "score" : 3,
        "contexts" : 
        [ 
          { "form" : "sunshine",
            "weight" : "1",
            "pos" : 177,
            "context" : "...of the aspen?—they have gathered to themselves the <mark>sunshine<\/mark> raining through the leaves, and the freshness on...",
            "fid" : "para13" },
          
          { "form" : "sunshine",
            "weight" : "1",
            "pos" : 1041,
            "context" : "...with her deeper feelings shrouded as it were in <mark>sunshine<\/mark>. What have she and Viola in common?...",
            "fid" : "para19" },
          
          { "form" : "sunshine",
            "weight" : "1",
            "pos" : 1504,
            "context" : "...hand. The fame is far off, and like <mark>sunshine<\/mark> seen in the distance, while only the cold...",
            "fid" : "para27" } ] },
      
      { "docId" : "LandonFemalePortraitIIIAliceLee",
        "docUri" : "LandonFemalePortraitIIIAliceLee.html",
        "score" : 3,
        "contexts" : 
        [ 
          { "form" : "sunshine",
            "weight" : "1",
            "pos" : 352,
            "context" : "...it is no longer easy to spring into the <mark>sunshine<\/mark>. We all grow wiser, but assuredly we...",
            "fid" : "para15" },
          
          { "form" : "sunshine",
            "weight" : "1",
            "pos" : 439,
            "context" : "...trees with the wind in their branches and the <mark>sunshine<\/mark> on their leaves. He caught his melody when...",
            "fid" : "para15" },
          
          { "form" : "sunshine",
            "weight" : "1",
            "pos" : 1010,
            "context" : "...in requital, 'God bless her!'\"21 There is <mark>sunshine<\/mark> in a shady place, and it is soothing...",
            "fid" : "para18" } ] },
      
      { "docId" : "LandonFemalePortraitIIConstance1838",
        "docUri" : "LandonFemalePortraitIIConstance1838.html",
        "score" : 1,
        "contexts" : 
        [ 
          { "form" : "sunshine",
            "weight" : "1",
            "pos" : 865,
            "context" : "...—a child, he must have played in the <mark>sunshine<\/mark> with spirits as light as the golden curls that...",
            "fid" : "para18" } ] },
      
      { "docId" : "BuskMMmeDudevantNovs1834",
        "docUri" : "BuskMMmeDudevantNovs1834.html",
        "score" : 1,
        "contexts" : 
        [ 
          { "form" : "sunshine",
            "weight" : "1",
            "pos" : 4681,
            "context" : "...gothic frame-work, glittered with light and <mark>sunshine<\/mark>; and the metal flowers heaped upon the shrines...",
            "fid" : "para151" } ] },
      
      { "docId" : "LandonFemalePortraitIFloraRose",
        "docUri" : "LandonFemalePortraitIFloraRose.html",
        "score" : 1,
        "contexts" : 
        [ 
          { "form" : "sunshine",
            "weight" : "1",
            "pos" : 1074,
            "context" : "...and kindly nature is brought out by happiness and <mark>sunshine<\/mark>. She would be content to gaze on the...",
            "fid" : "para23" } ] } ] }