
  { "stem" : "thunder",
    "instances" : 
    [ 
      { "docId" : "BarbCollins1797",
        "docUri" : "BarbCollins1797.html",
        "score" : 2,
        "contexts" : 
        [ 
          { "form" : "thunder",
            "weight" : "1",
            "pos" : 1856,
            "context" : "..., as, ecstatic wonder, listening the deep applauding <mark>thunder<\/mark>;32 and the description of the residence of...",
            "fid" : "para35" },
          
          { "form" : "thunder",
            "weight" : "1",
            "pos" : 3146,
            "context" : "...: the doubling drum, the sword thrown in <mark>thunder<\/mark> down, and the strained eyeball bursting from the head...",
            "fid" : "para49" } ] },
      
      { "docId" : "BarbMackenzieBritNov1810",
        "docUri" : "BarbMackenzieBritNov1810.html",
        "score" : 1,
        "contexts" : 
        [ 
          { "form" : "thunder",
            "weight" : "1",
            "pos" : 260,
            "context" : "..., when the ruffian's voice bursts upon him like <mark>thunder<\/mark>, and overwhelms them all with despair. Yet...",
            "fid" : "para16" } ] },
      
      { "docId" : "LandonFemalePortraitIIConstance1838",
        "docUri" : "LandonFemalePortraitIIConstance1838.html",
        "score" : 1,
        "contexts" : 
        [ 
          { "form" : "thunder",
            "weight" : "1",
            "pos" : 277,
            "context" : "...he wrote believed devoutly in the terrors of their <mark>thunder<\/mark>. But the guardian angels of England, Ireland...",
            "fid" : "para13" } ] },
      
      { "docId" : "ShelleyEngInItaly1826",
        "docUri" : "ShelleyEngInItaly1826.html",
        "score" : 1,
        "contexts" : 
        [ 
          { "form" : "thunder",
            "weight" : "1",
            "pos" : 3171,
            "context" : "...open into new abysses, with the crash of <mark>thunder<\/mark>, and reverberates from the wild rocks like the...",
            "fid" : "para30" } ] },
      
      { "docId" : "JewsburyLandonRev1831",
        "docUri" : "JewsburyLandonRev1831.html",
        "score" : 1,
        "contexts" : 
        [ 
          { "form" : "thunder",
            "weight" : "1",
            "pos" : 1058,
            "context" : "...of which called from its master a look of <mark>thunder<\/mark> and lightning up the table. To this succeeded...",
            "fid" : "para22" } ] },
      
      { "docId" : "LandonHemans1835",
        "docUri" : "LandonHemans1835.html",
        "score" : 1,
        "contexts" : 
        [ 
          { "form" : "thunder",
            "weight" : "1",
            "pos" : 1732,
            "context" : "...;27   but, like the azure glimpses between <mark>thunder<\/mark>-showers, the clouds gather more darkly around...",
            "fid" : "para29" } ] } ] }