
  { "stem" : "tunbridg",
    "instances" : 
    [ 
      { "docId" : "BarbLifeRichardson1804",
        "docUri" : "BarbLifeRichardson1804.html",
        "score" : 2,
        "contexts" : 
        [ 
          { "form" : "Tunbridge",
            "weight" : "1",
            "pos" : 13362,
            "context" : "...probably his country house, and the amusement of <mark>Tunbridge<\/mark>, which he was accustomed to frequent in the...",
            "fid" : "para152" },
          
          { "form" : "Tunbridge",
            "weight" : "1",
            "pos" : 15802,
            "context" : "...medicated airs of another, and the waters of <mark>Tunbridge<\/mark> with the sea-bathing places, and we...",
            "fid" : "para191" } ] } ] }