
  { "stem" : "whip",
    "instances" : 
    [ 
      { "docId" : "LandonBulwer1831",
        "docUri" : "LandonBulwer1831.html",
        "score" : 1,
        "contexts" : 
        [ 
          { "form" : "whip",
            "weight" : "1",
            "pos" : 4156,
            "context" : "19.  A <mark>whip<\/mark> for use in human punishment. Back",
            "fid" : "note19" } ] },
      
      { "docId" : "MoodyRevEqualled1790",
        "docUri" : "MoodyRevEqualled1790.html",
        "score" : 1,
        "contexts" : 
        [ 
          { "form" : "whips",
            "weight" : "1",
            "pos" : 203,
            "context" : "..., subdued, defenceless race; to read of <mark>whips<\/mark> and scourges, hard labour, short allowances of...",
            "fid" : "para14" } ] },
      
      { "docId" : "MoodyRevLettdeLaunai1806",
        "docUri" : "MoodyRevLettdeLaunai1806.html",
        "score" : 1,
        "contexts" : 
        [ 
          { "form" : "“whip",
            "weight" : "1",
            "pos" : 134,
            "context" : "...employed by the solitary inmates of a prison to <mark>“whip<\/mark> the lagging moments into speed.” We have heard...",
            "fid" : "para13" } ] },
      
      { "docId" : "JewsburyLandonRev1831",
        "docUri" : "JewsburyLandonRev1831.html",
        "score" : 1,
        "contexts" : 
        [ 
          { "form" : "whip",
            "weight" : "1",
            "pos" : 161,
            "context" : "...school, we have unfeignedly wished that she would <mark>whip<\/mark> some dozen of her scholars. The faults of...",
            "fid" : "para13" } ] } ] }