
  { "stem" : "xlv",
    "instances" : 
    [ 
      { "docId" : "BarbRichardBritNov1810",
        "docUri" : "BarbRichardBritNov1810.html",
        "score" : 1,
        "contexts" : 
        [ 
          { "form" : "xlv",
            "weight" : "1",
            "pos" : 5767,
            "context" : "..., he was constantly fed with adulation [Page <mark>xlv<\/mark>]and even his correspondencies with his male friends...",
            "fid" : "pg44" } ] },
      
      { "docId" : "LandonCritChateaubriand1836",
        "docUri" : "LandonCritChateaubriand1836.html",
        "score" : 1,
        "contexts" : 
        [ 
          { "form" : "XLV",
            "weight" : "1",
            "pos" : 2134,
            "context" : "...July 1835), pp. 319-36; and vol. <mark>XLV<\/mark>, no. 177 (September 1835), pp. 47-69....",
            "fid" : "note22" } ] },
      
      { "docId" : "BarbLifeRichardson1804",
        "docUri" : "BarbLifeRichardson1804.html",
        "score" : 1,
        "contexts" : 
        [ 
          { "form" : "xlv",
            "weight" : "1",
            "pos" : 2899,
            "context" : "...generosity of his dealings, soon gained [Page <mark>xlv<\/mark>] him friends, and his business greatly flourished...",
            "fid" : "pg38" } ] },
      
      { "docId" : "BarbSmithBritNov1810",
        "docUri" : "BarbSmithBritNov1810.html",
        "score" : 1,
        "contexts" : 
        [ 
          { "form" : "XLV",
            "weight" : "1",
            "pos" : 1046,
            "context" : "3.  Elegiac Sonnets, no. <mark>XLV<\/mark>. \"On Leaving a Part of Sussex\" 1-5 (...",
            "fid" : "note3" } ] },
      
      { "docId" : "MoodyRevLoveEpics1804",
        "docUri" : "MoodyRevLoveEpics1804.html",
        "score" : 1,
        "contexts" : 
        [ 
          { "form" : "xlv",
            "weight" : "1",
            "pos" : 594,
            "context" : "...par tout environnés App. Rev. Vol. <mark>xlv<\/mark>.L1[Page 514]Et, par tout l'entourant...",
            "fid" : "stanza5" } ] },
      
      { "docId" : "BarbCollins1797",
        "docUri" : "BarbCollins1797.html",
        "score" : 1,
        "contexts" : 
        [ 
          { "form" : "xlv",
            "weight" : "1",
            "pos" : 3580,
            "context" : "...been the first rough draught of the [Page <mark>xlv<\/mark>]Poem; it was written in the year...",
            "fid" : "pg42" } ] } ] }