
  { "stem" : "zeluco",
    "instances" : 
    [ 
      { "docId" : "BarbMooreBritNov1810",
        "docUri" : "BarbMooreBritNov1810.html",
        "score" : 9,
        "contexts" : 
        [ 
          { "form" : "Zeluco",
            "weight" : "1",
            "pos" : 19,
            "context" : "...of English growth, few possess greater excellence than <mark>Zeluco<\/mark>. Its author, John Moore, M.D.,...",
            "fid" : "para13" },
          
          { "form" : "Zeluco",
            "weight" : "1",
            "pos" : 269,
            "context" : "...under the form of a novel; and his <mark>Zeluco<\/mark>, which appeared in 1789, placed its author...",
            "fid" : "para14" },
          
          { "form" : "Zeluco",
            "weight" : "1",
            "pos" : 385,
            "context" : "...Manners in Italy. The favourable manner in which <mark>Zeluco<\/mark> had been received, induced its author to give...",
            "fid" : "para15" },
          
          { "form" : "Zeluco",
            "weight" : "1",
            "pos" : 475,
            "context" : " The novel of <mark>Zeluco<\/mark>, which appears in this selection, is one...",
            "fid" : "para17" },
          
          { "form" : "Zeluco",
            "weight" : "1",
            "pos" : 523,
            "context" : "..., who is a finished model of depravity. <mark>Zeluco<\/mark> is painted as radically vicious, without the intermixture...",
            "fid" : "para17" },
          
          { "form" : "Zeluco",
            "weight" : "1",
            "pos" : 791,
            "context" : "...will take up again and again Dr. Moore's <mark>Zeluco<\/mark>. ",
            "fid" : "para17" },
          
          { "form" : "Zeluco",
            "weight" : "1",
            "pos" : 799,
            "context" : "...publication of the kind, is much inferior to <mark>Zeluco<\/mark>: the best character in it is that of...",
            "fid" : "para18" },
          
          { "form" : "Zeluco",
            "weight" : "1",
            "pos" : 860,
            "context" : "...very languid production; both his novels subsequent to <mark>Zeluco<\/mark> are not only inferior in entertainment to his first...",
            "fid" : "para18" },
          
          { "form" : "Zeluco",
            "weight" : "1",
            "pos" : 1047,
            "context" : "9.  <mark>Zeluco<\/mark> (London: A. Strahan and T. Cadell,...",
            "fid" : "note9" } ] },
      
      { "docId" : "BarbRichardBritNov1810",
        "docUri" : "BarbRichardBritNov1810.html",
        "score" : 2,
        "contexts" : 
        [ 
          { "form" : "Zeluco",
            "weight" : "1",
            "pos" : 3112,
            "context" : "...was tried, and the virtue of the wife <mark>Zeluco<\/mark>6 was tried, [Page xxv]because...",
            "fid" : "para38" },
          
          { "form" : "Zeluco",
            "weight" : "1",
            "pos" : 6179,
            "context" : "...The Sorrows of Young Werther and John Moore's <mark>Zeluco<\/mark>, respectively. Back",
            "fid" : "note6" } ] },
      
      { "docId" : "people",
        "docUri" : "people.html",
        "score" : 1,
        "contexts" : 
        [ 
          { "form" : "Zeluco",
            "weight" : "1",
            "pos" : 31889,
            "context" : "...Titles by the author include his most popular novel <mark>Zeluco<\/mark> (1789), A View of Society and Manners..." } ] },
      
      { "docId" : "BarbOriginProgBritNov1810",
        "docUri" : "BarbOriginProgBritNov1810.html",
        "score" : 1,
        "contexts" : 
        [ 
          { "form" : "Zeluco",
            "weight" : "1",
            "pos" : 6166,
            "context" : "...comforts of life.34 It is probable in <mark>Zeluco<\/mark>35 that the detestable husband will some way or...",
            "fid" : "para53" } ] },
      
      { "docId" : "BarbLifeRichardson1804",
        "docUri" : "BarbLifeRichardson1804.html",
        "score" : 1,
        "contexts" : 
        [ 
          { "form" : "Zeluco",
            "weight" : "1",
            "pos" : 16304,
            "context" : "...The Sorrows of Young Werther and John Moore's <mark>Zeluco<\/mark>, respectively Back",
            "fid" : "note24" } ] } ] }